pyorchestratorclient/__init__.py
pyorchestratorclient/endpoints.py
pyorchestratorclient-3.2.4.1.dist-info/LICENSE
pyorchestratorclient-3.2.4.1.dist-info/METADATA
pyorchestratorclient-3.2.4.1.dist-info/WHEEL
pyorchestratorclient-3.2.4.1.dist-info/top_level.txt
pyorchestratorclient-3.2.4.1.dist-info/RECORD
