Metadata-Version: 2.1
Name: pyorchestratorclient
Version: 3.2.4.1
Summary: A simple Orchestrator API client
Home-page: https://github.com/ejortegau/python-orchestrator-client
Author: Eduardo J. Ortega U.
Author-email: github435@example.com
License: UNKNOWN
Project-URL: Bug Tracker, https://github.com/ejortegau/python-orchestrator-client/issues
Platform: UNKNOWN
Classifier: Programming Language :: Python :: 3
Classifier: License :: OSI Approved :: GNU Affero General Public License v3
Classifier: Operating System :: OS Independent
Requires-Python: >=3.8
Requires-Dist: requests
